deepl/__init__.py
deepl/__main__.py
deepl/api.py
deepl/extractors.py
deepl/generators.py
deepl/hacks.py
deepl/settings.py
deepl/utils.py
deepl_translate-1.2.0.dist-info/LICENSE
deepl_translate-1.2.0.dist-info/METADATA
deepl_translate-1.2.0.dist-info/WHEEL
deepl_translate-1.2.0.dist-info/entry_points.txt
deepl_translate-1.2.0.dist-info/top_level.txt
deepl_translate-1.2.0.dist-info/RECORD
