Metadata-Version: 2.1
Name: deepl-translate
Version: 1.2.0
Summary: UNKNOWN
Home-page: http://github.com/ptrstn/deepl-translate
Author: Peter Stein
License: MIT
Platform: UNKNOWN
Classifier: License :: OSI Approved :: MIT License
License-File: LICENSE
Requires-Dist: requests
